{"version": 0.6, "generator": "Overpass API 0.7.60 f4c14d41", "osm3s": {"timestamp_osm_base": "2023-05-01T18:11:54Z", "copyright": "The data included in this document is from www.openstreetmap.org. The data is made available under ODbL."}, "elements": [{"type": "node", "id": 215635507, "lat": 37.7978015, "lon": -76.5105177, "tags": {"power": "pole"}}, {"type": "node", "id": 215635512, "lat": 37.795219, "lon": -76.507009, "tags": {"power": "pole"}}, {"type": "node", "id": 215635516, "lat": 37.794665, "lon": -76.506332, "tags": {"power": "pole"}}, {"type": "node", "id": 215635520, "lat": 37.794586, "lon": -76.506259, "tags": {"power": "pole"}}, {"type": "node", "id": 215635523, "lat": 37.794482, "lon": -76.506147, "tags": {"power": "pole"}}, {"type": "node", "id": 215635526, "lat": 37.794086, "lon": -76.505648, "tags": {"power": "pole"}}, {"type": "node", "id": 215635529, "lat": 37.794016, "lon": -76.505541, "tags": {"power": "pole"}}, {"type": "node", "id": 215635533, "lat": 37.793938, "lon": -76.505449, "tags": {"power": "pole"}}, {"type": "node", "id": 215635538, "lat": 37.789475, "lon": -76.499539, "tags": {"power": "pole"}}, {"type": "node", "id": 215635541, "lat": 37.787622, "lon": -76.497081, "tags": {"power": "pole"}}, {"type": "node", "id": 215635543, "lat": 37.785184, "lon": -76.493917, "tags": {"power": "pole"}}, {"type": "node", "id": 215635550, "lat": 37.771143, "lon": -76.475578, "tags": {"power": "pole"}}, {"type": "node", "id": 215635555, "lat": 37.770858, "lon": -76.475207, "tags": {"power": "pole"}}, {"type": "node", "id": 215635559, "lat": 37.770254, "lon": -76.474445, "tags": {"power": "pole"}}, {"type": "node", "id": 215635562, "lat": 37.7695871, "lon": -76.4735089, "tags": {"power": "pole"}}, {"type": "node", "id": 215635565, "lat": 37.7676484, "lon": -76.4710101, "tags": {"power": "pole"}}, {"type": "node", "id": 215635569, "lat": 37.7674398, "lon": -76.4707293, "tags": {"power": "pole"}}, {"type": "node", "id": 215635577, "lat": 37.765469, "lon": -76.468175, "tags": {"power": "pole"}}, {"type": "node", "id": 215635580, "lat": 37.7573405, "lon": -76.4572473, "tags": {"power": "pole"}}, {"type": "node", "id": 215635585, "lat": 37.755497, "lon": -76.454434, "tags": {"power": "pole"}}, {"type": "node", "id": 215635589, "lat": 37.7501482, "lon": -76.4407455, "tags": {"power": "pole"}}, {"type": "node", "id": 215635593, "lat": 37.745896, "lon": -76.428966, "tags": {"power": "pole"}}, {"type": "node", "id": 215635596, "lat": 37.745596, "lon": -76.42821, "tags": {"power": "pole"}}, {"type": "node", "id": 215635600, "lat": 37.743426, "lon": -76.422123, "tags": {"power": "pole"}}, {"type": "node", "id": 215635604, "lat": 37.741563, "lon": -76.417088, "tags": {"power": "pole"}}, {"type": "node", "id": 215635608, "lat": 37.7397989, "lon": -76.411952, "tags": {"power": "pole"}}, {"type": "node", "id": 215635612, "lat": 37.738889, "lon": -76.409716, "tags": {"power": "pole"}}, {"type": "node", "id": 215635616, "lat": 37.737556, "lon": -76.406039, "tags": {"power": "pole"}}, {"type": "node", "id": 215635621, "lat": 37.737016, "lon": -76.404349, "tags": {"power": "pole"}}, {"type": "node", "id": 215635624, "lat": 37.734708, "lon": -76.403056, "tags": {"power": "pole"}}, {"type": "node", "id": 215635630, "lat": 37.7338188, "lon": -76.4026701, "tags": {"power": "pole"}}, {"type": "node", "id": 215635634, "lat": 37.731219, "lon": -76.401981, "tags": {"power": "pole"}}, {"type": "node", "id": 215635637, "lat": 37.7167653, "lon": -76.3956956, "tags": {"power": "pole"}}, {"type": "node", "id": 215635640, "lat": 37.7110154, "lon": -76.3930458, "tags": {"power": "pole"}}, {"type": "node", "id": 215635645, "lat": 37.709489, "lon": -76.3923523, "tags": {"power": "pole"}}, {"type": "node", "id": 215635649, "lat": 37.7087504, "lon": -76.3932766, "tags": {"power": "pole"}}, {"type": "node", "id": 215650481, "lat": 37.5437349, "lon": -76.7506388, "tags": {"power": "tower"}}, {"type": "node", "id": 215737751, "lat": 37.8342247, "lon": -76.5428031}, {"type": "node", "id": 215737755, "lat": 37.824977, "lon": -76.536348}, {"type": "node", "id": 215737756, "lat": 37.823994, "lon": -76.535639}, {"type": "node", "id": 215737760, "lat": 37.823808, "lon": -76.535507}, {"type": "node", "id": 215737764, "lat": 37.823585, "lon": -76.535349}, {"type": "node", "id": 215737768, "lat": 37.815109, "lon": -76.529291}, {"type": "node", "id": 215737772, "lat": 37.809994, "lon": -76.525623}, {"type": "node", "id": 215737775, "lat": 37.8093, "lon": -76.524908}, {"type": "node", "id": 215737779, "lat": 37.807406, "lon": -76.522935}, {"type": "node", "id": 215737783, "lat": 37.802657, "lon": -76.516728}, {"type": "node", "id": 215737787, "lat": 37.7992984, "lon": -76.5124549}, {"type": "node", "id": 215803379, "lat": 37.78045, "lon": -76.487772, "tags": {"power": "pole"}}, {"type": "node", "id": 218322830, "lat": 37.9455803, "lon": -76.7106496}, {"type": "node", "id": 218322832, "lat": 37.944591, "lon": -76.707859}, {"type": "node", "id": 218322835, "lat": 37.943687, "lon": -76.705947}, {"type": "node", "id": 218322838, "lat": 37.943501, "lon": -76.705586}, {"type": "node", "id": 218322841, "lat": 37.943375, "lon": -76.705312}, {"type": "node", "id": 218322842, "lat": 37.942058, "lon": -76.702669}, {"type": "node", "id": 218322845, "lat": 37.941316, "lon": -76.701112}, {"type": "node", "id": 218322852, "lat": 37.940617, "lon": -76.699735}, {"type": "node", "id": 218322854, "lat": 37.938738, "lon": -76.696395}, {"type": "node", "id": 218322856, "lat": 37.937962, "lon": -76.694953}, {"type": "node", "id": 218322858, "lat": 37.937189, "lon": -76.693093}, {"type": "node", "id": 218322860, "lat": 37.936549, "lon": -76.690886}, {"type": "node", "id": 218322862, "lat": 37.934624, "lon": -76.686891}, {"type": "node", "id": 218322864, "lat": 37.932297, "lon": -76.681861}, {"type": "node", "id": 218322866, "lat": 37.928701, "lon": -76.674094}, {"type": "node", "id": 218322870, "lat": 37.925265, "lon": -76.667247}, {"type": "node", "id": 218322873, "lat": 37.922512, "lon": -76.661102}, {"type": "node", "id": 218322875, "lat": 37.921846, "lon": -76.659615}, {"type": "node", "id": 218322878, "lat": 37.921817, "lon": -76.659539}, {"type": "node", "id": 218322881, "lat": 37.920439, "lon": -76.656474}, {"type": "node", "id": 218322884, "lat": 37.91881, "lon": -76.653057}, {"type": "node", "id": 218322889, "lat": 37.917583, "lon": -76.650341}, {"type": "node", "id": 218322893, "lat": 37.914164, "lon": -76.643317}, {"type": "node", "id": 218322897, "lat": 37.912027, "lon": -76.638633}, {"type": "node", "id": 218322900, "lat": 37.911438, "lon": -76.637496}, {"type": "node", "id": 218322903, "lat": 37.91006, "lon": -76.634481}, {"type": "node", "id": 218322906, "lat": 37.909647, "lon": -76.633588}, {"type": "node", "id": 218322907, "lat": 37.908847, "lon": -76.63188}, {"type": "node", "id": 218322910, "lat": 37.90538, "lon": -76.624639}, {"type": "node", "id": 218322913, "lat": 37.904111, "lon": -76.621982}, {"type": "node", "id": 218322915, "lat": 37.904048, "lon": -76.621852}, {"type": "node", "id": 218322918, "lat": 37.90403, "lon": -76.621815}, {"type": "node", "id": 218322921, "lat": 37.904016, "lon": -76.621775}, {"type": "node", "id": 218322924, "lat": 37.901164, "lon": -76.615842}, {"type": "node", "id": 218322928, "lat": 37.895836, "lon": -76.604638}, {"type": "node", "id": 218322935, "lat": 37.895819, "lon": -76.60459}, {"type": "node", "id": 218322936, "lat": 37.89581, "lon": -76.60457}, {"type": "node", "id": 218322939, "lat": 37.889418, "lon": -76.5903}, {"type": "node", "id": 218322942, "lat": 37.884839, "lon": -76.580829}, {"type": "node", "id": 218322945, "lat": 37.882879, "lon": -76.576608}, {"type": "node", "id": 218322947, "lat": 37.882536, "lon": -76.576365}, {"type": "node", "id": 218322949, "lat": 37.875139, "lon": -76.571121}, {"type": "node", "id": 218322951, "lat": 37.874525, "lon": -76.570811}, {"type": "node", "id": 218322953, "lat": 37.866339, "lon": -76.565109}, {"type": "node", "id": 218322955, "lat": 37.8635087, "lon": -76.5631313}, {"type": "node", "id": 218322957, "lat": 37.856389, "lon": -76.558299}, {"type": "node", "id": 218322959, "lat": 37.854118, "lon": -76.556724}, {"type": "node", "id": 218322962, "lat": 37.853726, "lon": -76.556443}, {"type": "node", "id": 218322965, "lat": 37.849957, "lon": -76.553841}, {"type": "node", "id": 218322968, "lat": 37.849029, "lon": -76.553191}, {"type": "node", "id": 218322972, "lat": 37.839452, "lon": -76.546543}, {"type": "node", "id": 956275722, "lat": 37.5822691, "lon": -76.4853469}, {"type": "node", "id": 956275723, "lat": 37.5862481, "lon": -76.4882008, "tags": {"power": "tower"}}, {"type": "node", "id": 956275725, "lat": 37.5822861, "lon": -76.4946595, "tags": {"power": "tower"}}, {"type": "node", "id": 956275727, "lat": 37.580305, "lon": -76.508725, "tags": {"power": "tower"}}, {"type": "node", "id": 956275728, "lat": 37.578613, "lon": -76.5201942, "tags": {"power": "tower"}}, {"type": "node", "id": 956275729, "lat": 37.5764532, "lon": -76.5349785, "tags": {"power": "tower"}}, {"type": "node", "id": 956275730, "lat": 37.5755009, "lon": -76.5411154, "tags": {"power": "tower"}}, {"type": "node", "id": 956275731, "lat": 37.5710424, "lon": -76.5574794, "tags": {"power": "tower"}}, {"type": "node", "id": 956275733, "lat": 37.5702791, "lon": -76.5602808, "tags": {"power": "tower"}}, {"type": "node", "id": 956275734, "lat": 37.5665295, "lon": -76.5740422, "tags": {"power": "tower"}}, {"type": "node", "id": 956275736, "lat": 37.5636551, "lon": -76.5775183, "tags": {"power": "tower"}}, {"type": "node", "id": 956275737, "lat": 37.5620647, "lon": -76.5888694, "tags": {"power": "tower"}}, {"type": "node", "id": 956275738, "lat": 37.561682, "lon": -76.5915624, "tags": {"power": "tower"}}, {"type": "node", "id": 956275739, "lat": 37.5612567, "lon": -76.5945665, "tags": {"power": "tower"}}, {"type": "node", "id": 956275740, "lat": 37.5602957, "lon": -76.6007677, "tags": {"power": "tower"}}, {"type": "node", "id": 956275742, "lat": 37.5589944, "lon": -76.6078809, "tags": {"power": "tower"}}, {"type": "node", "id": 956275744, "lat": 37.5548524, "lon": -76.6376106, "tags": {"power": "tower"}}, {"type": "node", "id": 956275746, "lat": 37.5530492, "lon": -76.6498843, "tags": {"power": "tower"}}, {"type": "node", "id": 956275747, "lat": 37.5511439, "lon": -76.6634563, "tags": {"power": "tower"}}, {"type": "node", "id": 956275748, "lat": 37.5503273, "lon": -76.6689817, "tags": {"power": "tower"}}, {"type": "node", "id": 956275749, "lat": 37.5500977, "lon": -76.6709236, "tags": {"power": "tower"}}, {"type": "node", "id": 956275750, "lat": 37.5497319, "lon": -76.6735414, "tags": {"power": "tower"}}, {"type": "node", "id": 956275752, "lat": 37.5490259, "lon": -76.6745928, "tags": {"power": "tower"}}, {"type": "node", "id": 956275753, "lat": 37.5431139, "lon": -76.6837016, "tags": {"power": "tower"}}, {"type": "node", "id": 956275755, "lat": 37.5436257, "lon": -76.6864227, "tags": {"power": "tower"}}, {"type": "node", "id": 956275756, "lat": 37.5441007, "lon": -76.688948, "tags": {"power": "tower"}}, {"type": "node", "id": 956275757, "lat": 37.5411573, "lon": -76.6981212, "tags": {"power": "tower"}}, {"type": "node", "id": 956275760, "lat": 37.5429267, "lon": -76.7016724, "tags": {"power": "tower"}}, {"type": "node", "id": 956275761, "lat": 37.5428696, "lon": -76.703558, "tags": {"power": "tower"}}, {"type": "node", "id": 956275762, "lat": 37.5427998, "lon": -76.7058662, "tags": {"power": "tower"}}, {"type": "node", "id": 956275764, "lat": 37.5427351, "lon": -76.708003, "tags": {"power": "tower"}}, {"type": "node", "id": 956275767, "lat": 37.5426652, "lon": -76.7103101, "tags": {"power": "tower"}}, {"type": "node", "id": 956275768, "lat": 37.5425889, "lon": -76.7128318, "tags": {"power": "tower"}}, {"type": "node", "id": 956275769, "lat": 37.5425168, "lon": -76.7152121, "tags": {"power": "tower"}}, {"type": "node", "id": 956275770, "lat": 37.5424382, "lon": -76.717808, "tags": {"power": "tower"}}, {"type": "node", "id": 956275771, "lat": 37.542296, "lon": -76.722507, "tags": {"power": "tower"}}, {"type": "node", "id": 956275772, "lat": 37.542076, "lon": -76.7297713, "tags": {"power": "tower"}}, {"type": "node", "id": 956275773, "lat": 37.5435278, "lon": -76.739089, "tags": {"power": "tower"}}, {"type": "node", "id": 956275774, "lat": 37.5439631, "lon": -76.7418824, "tags": {"power": "tower"}}, {"type": "node", "id": 956275775, "lat": 37.5442793, "lon": -76.7439119, "tags": {"power": "tower"}}, {"type": "node", "id": 956275776, "lat": 37.5439731, "lon": -76.7481444, "tags": {"power": "tower"}}, {"type": "node", "id": 1628977389, "lat": 37.7082706, "lon": -76.3937506, "tags": {"power": "pole"}}, {"type": "node", "id": 1628977419, "lat": 37.9470966, "lon": -76.7112839}, {"type": "node", "id": 1628977437, "lat": 37.9479074, "lon": -76.7118101}, {"type": "node", "id": 8147973864, "lat": 37.7705289, "lon": -76.4747664}, {"type": "node", "id": 8156817745, "lat": 37.7691404, "lon": -76.4729515, "tags": {"power": "pole"}}, {"type": "node", "id": 8156817746, "lat": 37.7682894, "lon": -76.4718601, "tags": {"power": "pole"}}, {"type": "node", "id": 8156817747, "lat": 37.7663855, "lon": -76.4693502, "tags": {"power": "pole"}}, {"type": "way", "id": 20315020, "nodes": [215635507, 215635512, 215635516, 215635520, 215635523, 215635526, 215635529, 215635533, 215635538, 215635541, 215635543, 215803379, 215635550, 215635555, 8147973864, 215635559, 215635562, 8156817745, 8156817746, 215635565, 215635569, 8156817747, 215635577, 215635580, 215635585, 215635589, 215635593, 215635596, 215635600, 215635604, 215635608, 215635612, 215635616, 215635621, 215635624, 215635630, 215635634, 215635637, 215635640, 215635645, 215635649, 1628977389], "tags": {"power": "line", "tiger:cfcc": "C20", "tiger:county": "Lancaster, VA", "tiger:reviewed": "no", "voltage": "115000"}}, {"type": "way", "id": 20320545, "nodes": [215737751, 215737755, 215737756, 215737760, 215737764, 215737768, 215737772, 215737775, 215737779, 215737783, 215737787, 215635507], "tags": {"power": "line", "tiger:cfcc": "C20", "tiger:county": "Lancaster, VA", "tiger:reviewed": "no", "tiger:source": "tiger_import_dch_v0.6_20070830", "tiger:tlid": "30796676:30796678:30796672:30808298:30808300:30808301:30808212:30808213", "tiger:upload_uuid": "bulk_upload.pl-566ecc12-0ca1-4e75-893a-cebb55196676", "voltage": "115000"}}, {"type": "way", "id": 82121047, "nodes": [956275722, 956275723, 956275725, 956275727, 956275728, 956275729, 956275730, 956275731, 956275733, 956275734, 956275736, 956275737, 956275738, 956275739, 956275740, 956275742, 956275744, 956275746, 956275747, 956275748, 956275749, 956275750, 956275752, 956275753, 956275755, 956275756, 956275757, 956275760, 956275761, 956275762, 956275764, 956275767, 956275768, 956275769, 956275770, 956275771, 956275772, 956275773, 956275774, 956275775, 956275776, 215650481], "tags": {"power": "line", "source": "Yahoo", "voltage": "230000"}}, {"type": "way", "id": 149961200, "nodes": [1628977437, 1628977419, 218322830, 218322832, 218322835, 218322838, 218322841, 218322842, 218322845, 218322852, 218322854, 218322856, 218322858, 218322860, 218322862, 218322864, 218322866, 218322870, 218322873, 218322875, 218322878, 218322881, 218322884, 218322889, 218322893, 218322897, 218322900, 218322903, 218322906, 218322907, 218322910, 218322913, 218322915, 218322918, 218322921, 218322924, 218322928, 218322935, 218322936, 218322939, 218322942, 218322945, 218322947, 218322949, 218322951, 218322953, 218322955, 218322957, 218322959, 218322962, 218322965, 218322968, 218322972, 215737751], "tags": {"power": "line", "tiger:cfcc": "C20", "tiger:county": "Richmond, VA", "tiger:reviewed": "no", "tiger:source": "tiger_import_dch_v0.6_20070830", "tiger:tlid": "22154714:22154715:22151987:22151989:22151530:22151532:22151534:22154488:22154489:22152169:22156740:22154584:22154585:22151991:22151993:22151995:22151997:22151999:22152089:22154484:22154485:22151059:22156077:22156078:22152087:22154474:22154475:22154476:221", "tiger:upload_uuid": "bulk_upload.pl-3dd01eba-ff1c-4bda-b665-f33a5fe21fbf", "voltage": "115000"}}]}